hblang/__init__.py
hblang/interpreter.py
hblang/logger.py
hblang-1.2.1.dist-info/METADATA
hblang-1.2.1.dist-info/WHEEL
hblang-1.2.1.dist-info/entry_points.txt
hblang-1.2.1.dist-info/top_level.txt
hblang-1.2.1.dist-info/RECORD
